jwt/__init__.py
jwt/exceptions.py
jwt/jwa.py
jwt/jwk.py
jwt/jwkset.py
jwt/jws.py
jwt/jwt.py
jwt/py.typed
jwt/utils.py
python_jwt_fork/__init__.py
python_jwt_fork/exceptions.py
python_jwt_fork/jwa.py
python_jwt_fork/jwk.py
python_jwt_fork/jwkset.py
python_jwt_fork/jws.py
python_jwt_fork/jwt.py
python_jwt_fork/py.typed
python_jwt_fork/utils.py
python_jwt_fork/tests/__init__.py
python_jwt_fork/tests/helper.py
python_jwt_fork/tests/test_jwa.py
python_jwt_fork/tests/test_jwk.py
python_jwt_fork/tests/test_jwkset.py
python_jwt_fork/tests/test_jws.py
python_jwt_fork/tests/test_jwt.py
python_jwt_fork/tests/test_utils.py
python_jwt_fork-1.3.1.dist-info/LICENSE
python_jwt_fork-1.3.1.dist-info/METADATA
python_jwt_fork-1.3.1.dist-info/WHEEL
python_jwt_fork-1.3.1.dist-info/top_level.txt
python_jwt_fork-1.3.1.dist-info/RECORD
